django_restricted_fields/VERSION
django_restricted_fields/__init__.py
django_restricted_fields/forms.py
django_restricted_fields-0.4.2.dist-info/licenses/LICENSE
django_restricted_fields-0.4.2.dist-info/WHEEL
django_restricted_fields-0.4.2.dist-info/METADATA
django_restricted_fields-0.4.2.dist-info/RECORD
